ipmi/__init__.py
ipmi/ipmi.py
ipmi/ipmicli.py
ipmitools-0.4.dist-info/LICENSE
ipmitools-0.4.dist-info/METADATA
ipmitools-0.4.dist-info/WHEEL
ipmitools-0.4.dist-info/entry_points.txt
ipmitools-0.4.dist-info/top_level.txt
ipmitools-0.4.dist-info/RECORD
