Metadata-Version: 2.1
Name: ipmitools
Version: 0.4
Summary: Run ipmitool commands on consoles
Home-page: https://github.com/raags/ipmitool
Author: Raghu Udiyar
Author-email: raghusiddarth@gmail.com
License: UNKNOWN
Download-URL: https://github.com/raags/ipmitool/tarball/0.4
Platform: UNKNOWN
Requires-Dist: pexpect
Requires-Dist: argparse
